lightspeed_connect/__init__.py
lightspeed_connect/client.py
lightspeed_connect/enums.py
lightspeed_connect/exceptions.py
lightspeed_connect/models.py
lightspeed_connect/utils.py
lightspeed_connect-0.1.0.dist-info/LICENSE
lightspeed_connect-0.1.0.dist-info/METADATA
lightspeed_connect-0.1.0.dist-info/WHEEL
lightspeed_connect-0.1.0.dist-info/RECORD
