Metadata-Version: 2.3
Name: lightspeed-connect
Version: 0.1.0
Summary: A Python client for connecting to Lightspeed's WebSocket API
License: MIT
Author: cdaviis
Author-email: chrisdavis179@gmail.com
Requires-Python: >=3.9
Classifier: License :: OSI Approved :: MIT License
Classifier: Programming Language :: Python :: 3
Classifier: Programming Language :: Python :: 3.9
Classifier: Programming Language :: Python :: 3.10
Classifier: Programming Language :: Python :: 3.11
Classifier: Programming Language :: Python :: 3.12
Classifier: Programming Language :: Python :: 3.13
Requires-Dist: websockets (>=12.0)
